[ {
  "name" : "INACTIVE",
  "sourceFieldname" : "INACTIVE",
  "description" : "INACTIVE",
  "dataType" : "number",
  "hasIndex" : false,
  "unique" : false,
  "primarykey" : false,
  "namefield" : false,
  "nullable" : false,
  "custom" : false,
  "createable" : true,
  "updateable" : true,
  "audit" : false,
  "customizable" : false,
  "fieldOrder" : 0,
  "fieldProperties" : {
    "autoGenerated" : "false"
  },
  "etag" : "675bc31d-b7ec-4279-9ea1-74e6369e530f",
  "isExtended" : false
}, {
  "name" : "ModifiedDate",
  "sourceFieldname" : "ModifiedDate",
  "description" : "ModifiedDate",
  "dataType" : "date",
  "hasIndex" : false,
  "unique" : false,
  "primarykey" : false,
  "namefield" : false,
  "nullable" : true,
  "custom" : false,
  "createable" : true,
  "updateable" : true,
  "audit" : false,
  "customizable" : false,
  "fieldOrder" : 0,
  "fieldProperties" : {
    "autoGenerated" : "false"
  },
  "etag" : "facc8d2c-045b-4511-840c-8fc2c5dc5bc3",
  "isExtended" : false
}, {
  "name" : "PartNo",
  "sourceFieldname" : "PartNo",
  "description" : "PartNo",
  "dataType" : "string",
  "hasIndex" : false,
  "unique" : false,
  "primarykey" : true,
  "namefield" : false,
  "nullable" : false,
  "custom" : false,
  "createable" : true,
  "updateable" : true,
  "audit" : false,
  "customizable" : false,
  "fieldLength" : 31,
  "fieldOrder" : 0,
  "fieldProperties" : {
    "autoGenerated" : "false"
  },
  "etag" : "cfa33836-2053-4588-bdcf-e7de448ef679",
  "isExtended" : false
}, {
  "name" : "Refrigerant",
  "sourceFieldname" : "Refrigerant",
  "description" : "Refrigerant",
  "dataType" : "string",
  "hasIndex" : false,
  "unique" : false,
  "primarykey" : false,
  "namefield" : false,
  "nullable" : false,
  "custom" : false,
  "createable" : true,
  "updateable" : true,
  "audit" : false,
  "customizable" : false,
  "fieldLength" : 15,
  "fieldOrder" : 0,
  "fieldProperties" : {
    "autoGenerated" : "false"
  },
  "etag" : "792e6276-1d6e-47c4-8b85-866d03a10a9d",
  "isExtended" : false
} ]