[ {
  "name" : "AssetBarCode",
  "sourceFieldname" : "AssetBarCode",
  "description" : "AssetBarCode",
  "dataType" : "string",
  "hasIndex" : false,
  "unique" : false,
  "primarykey" : false,
  "namefield" : false,
  "nullable" : false,
  "custom" : false,
  "createable" : true,
  "updateable" : true,
  "audit" : false,
  "customizable" : false,
  "fieldLength" : 50,
  "fieldOrder" : 1,
  "fieldProperties" : {
    "autoGenerated" : "false"
  },
  "etag" : "16727a30-18c3-4bb9-ab4b-e4e946c124fd",
  "isExtended" : false
}, {
  "name" : "Capacity",
  "sourceFieldname" : "Capacity",
  "description" : "Capacity",
  "dataType" : "number",
  "hasIndex" : false,
  "unique" : false,
  "primarykey" : false,
  "namefield" : false,
  "nullable" : false,
  "custom" : false,
  "createable" : true,
  "updateable" : true,
  "audit" : false,
  "customizable" : false,
  "fieldOrder" : 2,
  "fieldProperties" : {
    "autoGenerated" : "false"
  },
  "etag" : "15f44dc6-3718-4119-834a-a7f96be5e979",
  "isExtended" : false
}, {
  "name" : "CustSourceBarCode",
  "sourceFieldname" : "CustSourceBarCode",
  "description" : "CustSourceBarCode",
  "dataType" : "string",
  "hasIndex" : false,
  "unique" : false,
  "primarykey" : false,
  "namefield" : false,
  "nullable" : true,
  "custom" : false,
  "createable" : true,
  "updateable" : true,
  "audit" : false,
  "customizable" : false,
  "fieldLength" : 50,
  "fieldOrder" : 3,
  "fieldProperties" : {
    "autoGenerated" : "false"
  },
  "etag" : "2627cc4a-4cfd-44de-bf7f-c58b0c4ac0ae",
  "isExtended" : false
}, {
  "name" : "Description",
  "sourceFieldname" : "Description",
  "description" : "Description",
  "dataType" : "string",
  "hasIndex" : false,
  "unique" : false,
  "primarykey" : false,
  "namefield" : false,
  "nullable" : false,
  "custom" : false,
  "createable" : true,
  "updateable" : true,
  "audit" : false,
  "customizable" : false,
  "fieldLength" : 101,
  "fieldOrder" : 4,
  "fieldProperties" : {
    "autoGenerated" : "false"
  },
  "etag" : "ee14f8dd-3537-4b50-abd6-4963d4d92afa",
  "isExtended" : false
}, {
  "name" : "DeviceCreateDat",
  "sourceFieldname" : "DeviceCreateDate",
  "description" : "DeviceCreateDate",
  "dataType" : "date",
  "hasIndex" : false,
  "unique" : false,
  "primarykey" : false,
  "namefield" : false,
  "nullable" : true,
  "custom" : false,
  "createable" : true,
  "updateable" : true,
  "audit" : false,
  "customizable" : false,
  "fieldOrder" : 5,
  "fieldProperties" : {
    "autoGenerated" : "false"
  },
  "etag" : "d06ba213-462e-44fd-9d58-a7e95692a89a",
  "isExtended" : false
}, {
  "name" : "ID",
  "sourceFieldname" : "ID",
  "description" : "ID",
  "dataType" : "number",
  "hasIndex" : false,
  "unique" : false,
  "primarykey" : true,
  "namefield" : false,
  "nullable" : false,
  "custom" : false,
  "createable" : true,
  "updateable" : true,
  "audit" : false,
  "customizable" : false,
  "fieldOrder" : 6,
  "fieldProperties" : {
    "autoGenerated" : "true"
  },
  "etag" : "ae81149e-a739-4927-97b7-dafc6913fbeb",
  "isExtended" : false
}, {
  "name" : "KonyDeleteFlag",
  "sourceFieldname" : "KonyDeleteFlag",
  "description" : "KonyDeleteFlag",
  "dataType" : "number",
  "hasIndex" : false,
  "unique" : false,
  "primarykey" : false,
  "namefield" : false,
  "nullable" : true,
  "custom" : false,
  "createable" : true,
  "updateable" : true,
  "audit" : false,
  "customizable" : false,
  "fieldOrder" : 7,
  "fieldProperties" : {
    "autoGenerated" : "false"
  },
  "etag" : "ffeb781d-24a8-4557-945b-45fefb4b1bbd",
  "isExtended" : false
}, {
  "name" : "LastModified",
  "sourceFieldname" : "LastModified",
  "description" : "LastModified",
  "dataType" : "date",
  "hasIndex" : false,
  "unique" : false,
  "primarykey" : false,
  "namefield" : false,
  "nullable" : true,
  "custom" : false,
  "createable" : true,
  "updateable" : true,
  "audit" : false,
  "customizable" : false,
  "fieldOrder" : 8,
  "fieldProperties" : {
    "autoGenerated" : "false"
  },
  "etag" : "1e72185b-a6e0-4c1d-886b-2835a76d4285",
  "isExtended" : false
}, {
  "name" : "PartNo",
  "sourceFieldname" : "PartNo",
  "description" : "PartNo",
  "dataType" : "string",
  "hasIndex" : false,
  "unique" : false,
  "primarykey" : false,
  "namefield" : false,
  "nullable" : false,
  "custom" : false,
  "createable" : true,
  "updateable" : true,
  "audit" : false,
  "customizable" : false,
  "fieldLength" : 50,
  "fieldOrder" : 9,
  "fieldProperties" : {
    "autoGenerated" : "false"
  },
  "etag" : "b792677c-df3d-4434-9334-52b72709367a",
  "isExtended" : false
}, {
  "name" : "Qty",
  "sourceFieldname" : "Qty",
  "description" : "Qty",
  "dataType" : "number",
  "hasIndex" : false,
  "unique" : false,
  "primarykey" : false,
  "namefield" : false,
  "nullable" : true,
  "custom" : false,
  "createable" : true,
  "updateable" : true,
  "audit" : false,
  "customizable" : false,
  "fieldOrder" : 10,
  "fieldProperties" : {
    "autoGenerated" : "false"
  },
  "etag" : "caeb8363-3a4d-4c2f-9c8a-f450bbcaa98e",
  "isExtended" : false
}, {
  "name" : "ResolutionCode",
  "sourceFieldname" : "ResolutionCode",
  "description" : "ResolutionCode",
  "dataType" : "number",
  "hasIndex" : false,
  "unique" : false,
  "primarykey" : false,
  "namefield" : false,
  "nullable" : true,
  "custom" : false,
  "createable" : true,
  "updateable" : true,
  "audit" : false,
  "customizable" : false,
  "fieldOrder" : 11,
  "fieldProperties" : {
    "autoGenerated" : "false"
  },
  "etag" : "e5972d18-8ecb-487d-ba14-8b4512807324",
  "isExtended" : false
}, {
  "name" : "Source",
  "sourceFieldname" : "Source",
  "description" : "Source",
  "dataType" : "number",
  "hasIndex" : false,
  "unique" : false,
  "primarykey" : false,
  "namefield" : false,
  "nullable" : false,
  "custom" : false,
  "createable" : true,
  "updateable" : true,
  "audit" : false,
  "customizable" : false,
  "fieldOrder" : 12,
  "fieldProperties" : {
    "autoGenerated" : "false"
  },
  "etag" : "d1349b32-1aa0-4b0b-925e-26165bc79326",
  "isExtended" : false
}, {
  "name" : "Status",
  "sourceFieldname" : "Status",
  "description" : "Status",
  "dataType" : "number",
  "hasIndex" : false,
  "unique" : false,
  "primarykey" : false,
  "namefield" : false,
  "nullable" : false,
  "custom" : false,
  "createable" : true,
  "updateable" : true,
  "audit" : false,
  "customizable" : false,
  "fieldOrder" : 13,
  "fieldProperties" : {
    "autoGenerated" : "false"
  },
  "etag" : "5fae0370-c86b-4222-adbc-eaeb2a4ab3d8",
  "isExtended" : false
}, {
  "name" : "TechID",
  "sourceFieldname" : "TechID",
  "description" : "TechID",
  "dataType" : "string",
  "hasIndex" : false,
  "unique" : false,
  "primarykey" : false,
  "namefield" : false,
  "nullable" : false,
  "custom" : false,
  "createable" : true,
  "updateable" : true,
  "audit" : false,
  "customizable" : false,
  "fieldLength" : 20,
  "fieldOrder" : 14,
  "fieldProperties" : {
    "autoGenerated" : "false"
  },
  "etag" : "3e8d3dea-eaa1-4f77-9f2b-b1922da7e8d7",
  "isExtended" : false
}, {
  "name" : "WOID",
  "sourceFieldname" : "WO_ID",
  "description" : "WO_ID",
  "dataType" : "number",
  "hasIndex" : false,
  "unique" : false,
  "primarykey" : false,
  "namefield" : false,
  "nullable" : false,
  "custom" : false,
  "createable" : true,
  "updateable" : true,
  "audit" : false,
  "customizable" : false,
  "fieldOrder" : 15,
  "fieldProperties" : {
    "autoGenerated" : "false"
  },
  "etag" : "315cc9da-7ecc-4330-8032-e9cabc0bf9c2",
  "isExtended" : false
}, {
  "name" : "WorkOrderNo",
  "sourceFieldname" : "WorkOrderNo",
  "description" : "WorkOrderNo",
  "dataType" : "string",
  "hasIndex" : false,
  "unique" : false,
  "primarykey" : false,
  "namefield" : false,
  "nullable" : false,
  "custom" : false,
  "createable" : true,
  "updateable" : true,
  "audit" : false,
  "customizable" : false,
  "fieldLength" : 50,
  "fieldOrder" : 16,
  "fieldProperties" : {
    "autoGenerated" : "false"
  },
  "etag" : "9d81d4e5-83bd-45b8-b598-80809fe7365a",
  "isExtended" : false
} ]