[ {
  "name" : "CustSourceBarCode",
  "sourceFieldname" : "CustSourceBarCode",
  "description" : "CustSourceBarCode",
  "dataType" : "string",
  "hasIndex" : false,
  "unique" : false,
  "primarykey" : false,
  "namefield" : false,
  "nullable" : true,
  "custom" : false,
  "createable" : true,
  "updateable" : true,
  "audit" : false,
  "customizable" : false,
  "fieldLength" : 50,
  "fieldOrder" : 1,
  "fieldProperties" : {
    "autoGenerated" : "false"
  },
  "etag" : "4df7cdba-7654-4938-b6a3-6123d0622074",
  "isExtended" : false
}, {
  "name" : "DeviceCreateDat",
  "sourceFieldname" : "DeviceCreateDate",
  "description" : "DeviceCreateDate",
  "dataType" : "date",
  "hasIndex" : false,
  "unique" : false,
  "primarykey" : false,
  "namefield" : false,
  "nullable" : true,
  "custom" : false,
  "createable" : true,
  "updateable" : true,
  "audit" : false,
  "customizable" : false,
  "fieldOrder" : 2,
  "fieldProperties" : {
    "autoGenerated" : "false"
  },
  "etag" : "9d78323b-5645-4ce5-ac40-4cabdf614db1",
  "isExtended" : false
}, {
  "name" : "ID",
  "sourceFieldname" : "ID",
  "description" : "ID",
  "dataType" : "number",
  "hasIndex" : false,
  "unique" : false,
  "primarykey" : true,
  "namefield" : false,
  "nullable" : false,
  "custom" : false,
  "createable" : true,
  "updateable" : true,
  "audit" : false,
  "customizable" : false,
  "fieldOrder" : 3,
  "fieldProperties" : {
    "autoGenerated" : "true"
  },
  "etag" : "07b940bc-2ff5-43f7-ab5d-463059af4f59",
  "isExtended" : false
}, {
  "name" : "KonyDeleteFlag",
  "sourceFieldname" : "KonyDeleteFlag",
  "description" : "KonyDeleteFlag",
  "dataType" : "number",
  "hasIndex" : false,
  "unique" : false,
  "primarykey" : false,
  "namefield" : false,
  "nullable" : true,
  "custom" : false,
  "createable" : true,
  "updateable" : true,
  "audit" : false,
  "customizable" : false,
  "fieldOrder" : 4,
  "fieldProperties" : {
    "autoGenerated" : "false"
  },
  "etag" : "dc2b20df-4d7b-407e-93a8-c43c712ecae6",
  "isExtended" : false
}, {
  "name" : "LastModified",
  "sourceFieldname" : "LastModified",
  "description" : "LastModified",
  "dataType" : "date",
  "hasIndex" : false,
  "unique" : false,
  "primarykey" : false,
  "namefield" : false,
  "nullable" : true,
  "custom" : false,
  "createable" : true,
  "updateable" : true,
  "audit" : false,
  "customizable" : false,
  "fieldOrder" : 5,
  "fieldProperties" : {
    "autoGenerated" : "false"
  },
  "etag" : "e1c82580-f9dd-46d8-a3ea-50fef51fd634",
  "isExtended" : false
}, {
  "name" : "Qty",
  "sourceFieldname" : "Qty",
  "description" : "Qty",
  "dataType" : "number",
  "hasIndex" : false,
  "unique" : false,
  "primarykey" : false,
  "namefield" : false,
  "nullable" : true,
  "custom" : false,
  "createable" : true,
  "updateable" : true,
  "audit" : false,
  "customizable" : false,
  "fieldOrder" : 6,
  "fieldProperties" : {
    "autoGenerated" : "false"
  },
  "etag" : "43b19c58-4cfd-4deb-bd89-b9fef6e3df60",
  "isExtended" : false
}, {
  "name" : "RefrigerantID",
  "sourceFieldname" : "RefrigerantID",
  "description" : "RefrigerantID",
  "dataType" : "number",
  "hasIndex" : false,
  "unique" : false,
  "primarykey" : false,
  "namefield" : false,
  "nullable" : false,
  "custom" : false,
  "createable" : true,
  "updateable" : true,
  "audit" : false,
  "customizable" : false,
  "fieldOrder" : 7,
  "fieldProperties" : {
    "autoGenerated" : "false"
  },
  "etag" : "a6c09572-7a5f-4ef0-87c5-9684b98ed0d3",
  "isExtended" : false
}, {
  "name" : "Source",
  "sourceFieldname" : "Source",
  "description" : "Source",
  "dataType" : "number",
  "hasIndex" : false,
  "unique" : false,
  "primarykey" : false,
  "namefield" : false,
  "nullable" : false,
  "custom" : false,
  "createable" : true,
  "updateable" : true,
  "audit" : false,
  "customizable" : false,
  "fieldOrder" : 8,
  "fieldProperties" : {
    "autoGenerated" : "false"
  },
  "etag" : "df792413-e3b3-432b-90e2-fb1b9b69f0b4",
  "isExtended" : false
}, {
  "name" : "Status",
  "sourceFieldname" : "Status",
  "description" : "Status",
  "dataType" : "number",
  "hasIndex" : false,
  "unique" : false,
  "primarykey" : false,
  "namefield" : false,
  "nullable" : false,
  "custom" : false,
  "createable" : true,
  "updateable" : true,
  "audit" : false,
  "customizable" : false,
  "fieldOrder" : 9,
  "fieldProperties" : {
    "autoGenerated" : "false"
  },
  "etag" : "1ca1fa46-044c-4d50-b651-0a586555d8a3",
  "isExtended" : false
}, {
  "name" : "WOID",
  "sourceFieldname" : "WO_ID",
  "description" : "WO_ID",
  "dataType" : "number",
  "hasIndex" : false,
  "unique" : false,
  "primarykey" : false,
  "namefield" : false,
  "nullable" : false,
  "custom" : false,
  "createable" : true,
  "updateable" : true,
  "audit" : false,
  "customizable" : false,
  "fieldOrder" : 10,
  "fieldProperties" : {
    "autoGenerated" : "false"
  },
  "etag" : "6facfa11-633c-4357-a0aa-bd4e0b01e382",
  "isExtended" : false
}, {
  "name" : "WorkOrderAssetI",
  "sourceFieldname" : "WorkOrderAsset_ID",
  "description" : "WorkOrderAsset_ID",
  "dataType" : "number",
  "hasIndex" : false,
  "unique" : false,
  "primarykey" : false,
  "namefield" : false,
  "nullable" : true,
  "custom" : false,
  "createable" : true,
  "updateable" : true,
  "audit" : false,
  "customizable" : false,
  "fieldOrder" : 11,
  "fieldProperties" : {
    "autoGenerated" : "false"
  },
  "etag" : "e87e4e8f-b7d7-4042-9642-b1f57da2bd1f",
  "isExtended" : false
} ]